egasp/__init__.py
egasp/__main__.py
egasp/check_version.py
egasp/core.py
egasp/logger_config.py
egasp/validate.py
egasp/version.py
egasp/data/egasp_data.py
egasp-0.1.9.dist-info/licenses/LICENSE
egasp-0.1.9.dist-info/METADATA
egasp-0.1.9.dist-info/WHEEL
egasp-0.1.9.dist-info/entry_points.txt
egasp-0.1.9.dist-info/top_level.txt
egasp-0.1.9.dist-info/RECORD
