Metadata-Version: 2.4
Name: egasp
Version: 0.1.9
Summary: 乙二醇水溶液属性查询程序 Ethylene Glycol Aqueous Solution Properties Program
Author-email: 焱铭 <lxb-yanming@foxmail.com>
License-Expression: GPL-3.0-or-later
Project-URL: Homepage, https://github.com/YanMing-lxb/egasp
Project-URL: Bug Tracker, https://github.com/YanMing-lxb/egasp/issues
Keywords: Ethylene Glycol,Properties
Classifier: Environment :: Console
Classifier: Intended Audience :: Developers
Classifier: Intended Audience :: End Users/Desktop
Classifier: Intended Audience :: Education
Classifier: Intended Audience :: Science/Research
Classifier: Programming Language :: Python :: 3.9
Classifier: Programming Language :: Python :: 3.10
Classifier: Programming Language :: Python :: 3.11
Classifier: Programming Language :: Python :: 3.12
Classifier: Operating System :: OS Independent
Requires-Python: >=3.9
License-File: LICENSE
Requires-Dist: rich>=14.0.0
Requires-Dist: rich-argparse>=1.7.1
Requires-Dist: toml>=0.10.2
Requires-Dist: packaging>=25.0
Requires-Dist: platformdirs>=4.3.8
Requires-Dist: numpy>=2.0.2
Dynamic: license-file
